LICENSE
MANIFEST.in
README.rst
setup.cfg
setup.py
django_template_minifying_loader.egg-info/PKG-INFO
django_template_minifying_loader.egg-info/SOURCES.txt
django_template_minifying_loader.egg-info/dependency_links.txt
django_template_minifying_loader.egg-info/top_level.txt
template_minifying_loader/__init__.py
template_minifying_loader/utils.py
template_minifying_loader/loaders/__init__.py
template_minifying_loader/loaders/app_directories.py
template_minifying_loader/loaders/filesystem.py