Metadata-Version: 1.1
Name: django-template-minifying-loader
Version: 1.1
Summary: Simple Django template loader that minifies html output.
Home-page: https://github.com/SectorLabs/django-template-minifying-loader
Author: Sector Labs
Author-email: open-source@sectorlabs.ro
License: MIT License
Keywords: django,template,minification,html,minifier
Platform: UNKNOWN
Classifier: Environment :: Web Environment
Classifier: Framework :: Django
Classifier: Intended Audience :: Developers
Classifier: License :: OSI Approved :: MIT License
Classifier: Operating System :: OS Independent
Classifier: Programming Language :: Python
Classifier: Programming Language :: Python :: 3.5
Classifier: Topic :: Internet :: WWW/HTTP
Classifier: Topic :: Internet :: WWW/HTTP :: Dynamic Content
